odoo/addons/ssi_bad_debt_allowance/README.rst
odoo/addons/ssi_bad_debt_allowance/__init__.py
odoo/addons/ssi_bad_debt_allowance/__manifest__.py
odoo/addons/ssi_bad_debt_allowance/data/account_journal_data.xml
odoo/addons/ssi_bad_debt_allowance/data/approval_template_data.xml
odoo/addons/ssi_bad_debt_allowance/data/ir_sequence_data.xml
odoo/addons/ssi_bad_debt_allowance/data/policy_template_data.xml
odoo/addons/ssi_bad_debt_allowance/data/sequence_template_data.xml
odoo/addons/ssi_bad_debt_allowance/models/__init__.py
odoo/addons/ssi_bad_debt_allowance/models/bad_debt_allowance.py
odoo/addons/ssi_bad_debt_allowance/models/bad_debt_allowance_detail.py
odoo/addons/ssi_bad_debt_allowance/models/bad_debt_allowance_type.py
odoo/addons/ssi_bad_debt_allowance/models/bad_debt_allowance_type_percentage.py
odoo/addons/ssi_bad_debt_allowance/security/ir.model.access.csv
odoo/addons/ssi_bad_debt_allowance/security/ir_module_category_data.xml
odoo/addons/ssi_bad_debt_allowance/security/ir_rule_data.xml
odoo/addons/ssi_bad_debt_allowance/security/res_group_data.xml
odoo/addons/ssi_bad_debt_allowance/static/description/icon.png
odoo/addons/ssi_bad_debt_allowance/views/bad_debt_allowance_type_view.xml
odoo/addons/ssi_bad_debt_allowance/views/bad_debt_allowance_view.xml
odoo14_addon_ssi_bad_debt_allowance-14.0.1.0.2.dev1.dist-info/METADATA
odoo14_addon_ssi_bad_debt_allowance-14.0.1.0.2.dev1.dist-info/WHEEL
odoo14_addon_ssi_bad_debt_allowance-14.0.1.0.2.dev1.dist-info/top_level.txt
odoo14_addon_ssi_bad_debt_allowance-14.0.1.0.2.dev1.dist-info/RECORD
